swarmprediction/__init__.py
swarmprediction/nothing.py
swarmprediction-0.0.1.dist-info/LICENSE
swarmprediction-0.0.1.dist-info/METADATA
swarmprediction-0.0.1.dist-info/WHEEL
swarmprediction-0.0.1.dist-info/entry_points.txt
swarmprediction-0.0.1.dist-info/top_level.txt
swarmprediction-0.0.1.dist-info/RECORD
